pychemist/__init__.py
pychemist/version.py
pychemist/data/financials.parquet
pychemist-0.0.12.dist-info/licenses/LICENSE
pychemist-0.0.12.dist-info/METADATA
pychemist-0.0.12.dist-info/WHEEL
pychemist-0.0.12.dist-info/top_level.txt
pychemist-0.0.12.dist-info/RECORD
