Metadata-Version: 2.4
Name: Pychemist
Version: 0.0.12
Summary: Transform raw data into insights.
Author-email: Jeroen van Raak <j.j.f.vanraak@uva.nl>
License: Copyright (c) 2025 Jeroen van Raak
Project-URL: Homepage, https://github.com/vanraak/pychemist
Classifier: Programming Language :: Python :: 3
Classifier: License :: OSI Approved :: MIT License
Classifier: Operating System :: OS Independent
Requires-Python: >=3.8
License-File: LICENSE
Requires-Dist: pandas>=2.0
Requires-Dist: statsmodels
Requires-Dist: scipy
Dynamic: license-file
